{
  "generatedAt": "2026-06-10T15:31:15.120Z",
  "games": [
    {
      "id": "g1",
      "steamAppId": 3472040,
      "rating": 4,
      "title": "NBA 2K26",
      "desc": "Oferta especial de NBA 2K26 en GMG. Un juego imprescindible que no puede faltar en tu biblioteca.",
      "descEN": "Special offer for NBA 2K26 on GMG. An essential game that shouldn't be missing from your library.",
      "deals": [
        {
          "store": "GMG",
          "price": 8.04,
          "original": 69.99,
          "url": "https://www.cheapshark.com/redirect?dealID=dua6N5u4HYIU5lUexFlvkjLixz5RHy0a4lzdZENh64A%3D"
        }
      ]
    },
    {
      "id": "g2",
      "steamAppId": 2211170,
      "rating": 4,
      "title": "Unrailed 2: Back on Track",
      "desc": "Oferta especial de Unrailed 2: Back on Track en Steam. Un juego imprescindible que no puede faltar en tu biblioteca.",
      "descEN": "Special offer for Unrailed 2: Back on Track on Steam. An essential game that shouldn't be missing from your library.",
      "deals": [
        {
          "store": "Steam",
          "price": 18.38,
          "original": 31.98,
          "url": "https://www.cheapshark.com/redirect?dealID=%2BBTrEsQhJi0CANx8Tr0%2BEAXawizxUcm%2BWOIoA2eMObs%3D"
        }
      ]
    },
    {
      "id": "g3",
      "steamAppId": 1691190,
      "rating": 4,
      "title": "Rogue Waters",
      "desc": "Rogue Waters está en oferta en Epic. Consigue este título a un precio rebajado y disfruta de horas de diversión.",
      "descEN": "Take advantage of the Rogue Waters deal on Epic. A great game at an incredible price, available for a limited time.",
      "deals": [
        {
          "store": "Epic",
          "price": 0,
          "original": 29.99,
          "url": "https://www.cheapshark.com/redirect?dealID=ClaWCBpdtno5iYF3RyVR3%2BVXy71YWsZyoTRBxTQIwu8%3D"
        }
      ]
    },
    {
      "id": "g4",
      "steamAppId": 867210,
      "rating": 4,
      "title": "Songs of Conquest",
      "desc": "Songs of Conquest está en oferta en Epic. Consigue este título a un precio rebajado y disfruta de horas de diversión.",
      "descEN": "Take advantage of the Songs of Conquest deal on Epic. A great game at an incredible price, available for a limited time.",
      "deals": [
        {
          "store": "Epic",
          "price": 0,
          "original": 29.99,
          "url": "https://www.cheapshark.com/redirect?dealID=VF9sdPJEhhDS8Uredt4kVc5wic%2FIQUQ%2Bf0KV81VYRps%3D"
        }
      ]
    },
    {
      "id": "g5",
      "steamAppId": null,
      "rating": 4,
      "title": "RAVEN2 Half anniversary Starter Pack",
      "desc": "Encuentra RAVEN2 Half anniversary Starter Pack al mejor precio en Epic. No dejes pasar esta oportunidad única de añadirlo a tu colección.",
      "descEN": "Find RAVEN2 Half anniversary Starter Pack at the best price on Epic. Don't miss this unique opportunity to add it to your collection.",
      "deals": [
        {
          "store": "Epic",
          "price": 0,
          "original": 69.99,
          "url": "https://www.cheapshark.com/redirect?dealID=x8bu%2Bj%2BU0BedyBq04YtFGW%2BtW7TOdNYGp628gWMVceE%3D"
        },
        {
          "store": "GOG",
          "price": 6.95,
          "original": 69.5,
          "url": "https://www.cheapshark.com/redirect?dealID=Tp8gemBsqhKHEqPDDOz5JOjPlwucgGPN%2FcrwDnWT%2FGE%3D"
        },
        {
          "store": "GOG",
          "price": 8.25,
          "original": 82.65,
          "url": "https://www.cheapshark.com/redirect?dealID=%2BrHIxXrBkRZrZD5%2F7i0d%2BTDCEt%2BITRS6i%2BM7Muf0NQk%3D"
        },
        {
          "store": "GOG",
          "price": 6.39,
          "original": 69.99,
          "url": "https://www.cheapshark.com/redirect?dealID=KK3hWmzMGACZZq9c1BOzo8e4%2B1TpW%2FQpKS2K21%2FLbF4%3D"
        },
        {
          "store": "GMG",
          "price": 1.29,
          "original": 29.99,
          "url": "https://www.cheapshark.com/redirect?dealID=QZfYsy910uPsoXaQTF654pgEDbQ%2BMP5FVcg8LEsbfAY%3D"
        },
        {
          "store": "GMG",
          "price": 9.45,
          "original": 69.99,
          "url": "https://www.cheapshark.com/redirect?dealID=Kb%2BnKWG5d0q31D7pg5D0qPXKbHSfb210HrYKC%2FYe%2Bjw%3D"
        }
      ]
    },
    {
      "id": "g6",
      "steamAppId": 315210,
      "rating": 3,
      "title": "Suicide Squad: Kill the Justice League",
      "desc": "Encuentra Suicide Squad: Kill the Justice League al mejor precio en Epic. No dejes pasar esta oportunidad única de añadirlo a tu colección.",
      "descEN": "Take advantage of the Suicide Squad: Kill the Justice League deal on Epic. A great game at an incredible price, available for a limited time.",
      "deals": [
        {
          "store": "Epic",
          "price": 3.49,
          "original": 69.99,
          "url": "https://www.cheapshark.com/redirect?dealID=oyadBOu1z6MVss1%2BMfCBqCSpNd8cUcuA9cl2j7PtgMc%3D"
        }
      ]
    },
    {
      "id": "g7",
      "steamAppId": 75825,
      "rating": 4,
      "title": "The Incredible Adventures of Van Helsing Anthology",
      "desc": "Aprovecha la oferta de The Incredible Adventures of Van Helsing Anthology en Epic. Un gran juego a un precio increíble, disponible por tiempo limitado.",
      "descEN": "The Incredible Adventures of Van Helsing Anthology is on sale on Epic. Get this title at a reduced price and enjoy hours of fun.",
      "deals": [
        {
          "store": "Epic",
          "price": 7.49,
          "original": 74.99,
          "url": "https://www.cheapshark.com/redirect?dealID=1F%2Fs0kTRNaj6kR1b%2Fc7nUJHql%2FiZ3IW1pWHnXEOwVX4%3D"
        }
      ]
    }
  ],
  "news": [
    {
      "id": "n1",
      "title": "Despite reports and a video takedown, Gears of War: E-Day developers insist it was never in development for PS5",
      "titleEN": "Despite reports and a video takedown, Gears of War: E-Day developers insist it was never in development for PS5",
      "desc": "Gears of War: E-Day showed off incredibly well during last Sunday's Xbox Games Showcase. The show opened with a meaty first look at gameplay, before we were later treated to a much deeper dive into the upcoming prequel in a dedicated Direct. Read mor",
      "descEN": "Gears of War: E-Day showed off incredibly well during last Sunday's Xbox Games Showcase. The show opened with a meaty first look at gameplay, before we were later treated to a much deeper dive into the upcoming prequel in a dedicated Direct. Read mor",
      "date": "10 de junio de 2026",
      "source": "eurogamer.net",
      "tag": "Hardware"
    },
    {
      "id": "n2",
      "title": "Gears of War: E-Day is making big changes to one of the series' most iconic mechanics",
      "titleEN": "Gears of War: E-Day is making big changes to one of the series' most iconic mechanics",
      "desc": "You can really tell that Gears of War: E-Day developer, The Coalition, wants the upcoming third-person shooter to be enjoyed by more than just Gears diehards. In last Sunday's developer Direct, the studio recalled the decision to start development fr",
      "descEN": "You can really tell that Gears of War: E-Day developer, The Coalition, wants the upcoming third-person shooter to be enjoyed by more than just Gears diehards. In last Sunday's developer Direct, the studio recalled the decision to start development fr",
      "date": "10 de junio de 2026",
      "source": "eurogamer.net",
      "tag": "Noticia"
    },
    {
      "id": "n3",
      "title": "\"It's coming\" Gears of War: E-Day developer reassures multiplayer fans that more information is on the way",
      "titleEN": "\"It's coming\" Gears of War: E-Day developer reassures multiplayer fans that more information is on the way",
      "desc": "Gears of War: E-Day developers have reassured fans that multiplayer information is coming soon, following the game's single player-focused Xbox Game Showcase appearance. Read more",
      "descEN": "Gears of War: E-Day developers have reassured fans that multiplayer information is coming soon, following the game's single player-focused Xbox Game Showcase appearance. Read more",
      "date": "10 de junio de 2026",
      "source": "eurogamer.net",
      "tag": "Hardware"
    },
    {
      "id": "n4",
      "title": "Despite its trailer, Capcom says its Resident Evil - Code: Veronica remake is third-person and taking its cue from Resident Evil 2",
      "titleEN": "Despite its trailer, Capcom says its Resident Evil - Code: Veronica remake is third-person and taking its cue from Resident Evil 2",
      "desc": "If you saw Resident Evil Veronica's announcement trailer during last week's Summer Game Fest, you might reasonably assume it'll be continuing the modern series' forays into first-person horror. However, Capcom has now confirmed its Code Veronica rema",
      "descEN": "If you saw Resident Evil Veronica's announcement trailer during last week's Summer Game Fest, you might reasonably assume it'll be continuing the modern series' forays into first-person horror. However, Capcom has now confirmed its Code Veronica rema",
      "date": "10 de junio de 2026",
      "source": "eurogamer.net",
      "tag": "Noticia"
    },
    {
      "id": "n5",
      "title": "Wondering why Resident Evil Veronica has ditched the \"Code\" from the original's name? Capcom explains all",
      "titleEN": "Wondering why Resident Evil Veronica has ditched the \"Code\" from the original's name? Capcom explains all",
      "desc": "In all the excitement surrounding the announcement of Capcom's long-awaited Resident Evil Code Veronica remake last week, it was pretty easy to miss the fact its do-over has had a bit of a name change. And if you've been wondering why that might be, ",
      "descEN": "In all the excitement surrounding the announcement of Capcom's long-awaited Resident Evil Code Veronica remake last week, it was pretty easy to miss the fact its do-over has had a bit of a name change. And if you've been wondering why that might be, ",
      "date": "10 de junio de 2026",
      "source": "eurogamer.net",
      "tag": "Noticia"
    },
    {
      "id": "n6",
      "title": "Lord help me, Fable's behind-closed-doors demo has got me very excited",
      "titleEN": "Lord help me, Fable's behind-closed-doors demo has got me very excited",
      "desc": "It wouldn't be a Fable preview if I wasn't at least a little bit wary of encouraging you to get your hopes up. But, forgive me, I'm going to. I've seen a good half hour of continuous gameplay and, although it comes with plenty of caveats, it really w",
      "descEN": "It wouldn't be a Fable preview if I wasn't at least a little bit wary of encouraging you to get your hopes up. But, forgive me, I'm going to. I've seen a good half hour of continuous gameplay and, although it comes with plenty of caveats, it really w",
      "date": "10 de junio de 2026",
      "source": "eurogamer.net",
      "tag": "Noticia"
    },
    {
      "id": "n7",
      "title": "I went into Halo: Campaign Evolved thinking it didn't need to exist, but after playing two levels I want full remakes of the original trilogy and Reach",
      "titleEN": "I went into Halo: Campaign Evolved thinking it didn't need to exist, but after playing two levels I want full remakes of the original trilogy and Reach",
      "desc": "When Microsoft revealed that Halo: Campaign Evolved last year, I balked at its claim that this would be \"a faithful yet modernised remake of Halo: Combat Evolved's campaign\". How could it be? It's made in Unreal Engine 5, very few of the original tea",
      "descEN": "When Microsoft revealed that Halo: Campaign Evolved last year, I balked at its claim that this would be \"a faithful yet modernised remake of Halo: Combat Evolved's campaign\". How could it be? It's made in Unreal Engine 5, very few of the original tea",
      "date": "10 de junio de 2026",
      "source": "eurogamer.net",
      "tag": "Noticia"
    },
    {
      "id": "n8",
      "title": "Physical Steam gift cards are being ended by Valve because scammers keep using them to trick people",
      "titleEN": "Physical Steam gift cards are being ended by Valve because scammers keep using them to trick people",
      "desc": "One of the most popular ways for Steam users to charge their store wallets is through the purchase of gift cards. For years, Steam has allowed players to purchase gift cards in different denominations, which they could then redeem for their value on ",
      "descEN": "One of the most popular ways for Steam users to charge their store wallets is through the purchase of gift cards. For years, Steam has allowed players to purchase gift cards in different denominations, which they could then redeem for their value on ",
      "date": "10 de junio de 2026",
      "source": "eurogamer.net",
      "tag": "Noticia"
    },
    {
      "id": "n9",
      "title": "The Dragon's Dogma 2 expansion and Switch 2 port provide Capcom with a perfect opportunity to substantially update the game - and work has already begun",
      "titleEN": "The Dragon's Dogma 2 expansion and Switch 2 port provide Capcom with a perfect opportunity to substantially update the game - and work has already begun",
      "desc": "The reveal of a Dragon's Dogma 2 port for Nintendo Switch 2 was one of the biggest surprises  in yesterday's Nintendo Direct. Moreover, it's the Dark Arisen version that includes a new expansion also coming to other versions of the game. And Capcom i",
      "descEN": "The reveal of a Dragon's Dogma 2 port for Nintendo Switch 2 was one of the biggest surprises  in yesterday's Nintendo Direct. Moreover, it's the Dark Arisen version that includes a new expansion also coming to other versions of the game. And Capcom i",
      "date": "10 de junio de 2026",
      "source": "eurogamer.net",
      "tag": "Expansión"
    },
    {
      "id": "n10",
      "title": "With Guild Wars 3 announced at long last, here's why its beloved predecessor has survived the test of time",
      "titleEN": "With Guild Wars 3 announced at long last, here's why its beloved predecessor has survived the test of time",
      "desc": "This year's Summer Game Fest was packed full of plenty of great reveals, but for my money, Guild Wars 3 was one of the biggest bombshells. There had been whisperings of its existence, a few stray job postings here and there, but to actually see it on",
      "descEN": "This year's Summer Game Fest was packed full of plenty of great reveals, but for my money, Guild Wars 3 was one of the biggest bombshells. There had been whisperings of its existence, a few stray job postings here and there, but to actually see it on",
      "date": "10 de junio de 2026",
      "source": "eurogamer.net",
      "tag": "Noticia"
    },
    {
      "id": "n11",
      "title": "\"It's not just one definition or meaning\" - legendary designer Fumito Ueda says Gen Atlas, the title of his new game, means more than you might think",
      "titleEN": "\"It's not just one definition or meaning\" - legendary designer Fumito Ueda says Gen Atlas, the title of his new game, means more than you might think",
      "desc": "Fumito Ueda - the legendary designer of ICO, Shadow of the Colossus and The Last Guardian - has explained what the title of his new game, Gen Atlas, means. And it seems like it carries more meaning than you might think. Read more",
      "descEN": "Fumito Ueda - the legendary designer of ICO, Shadow of the Colossus and The Last Guardian - has explained what the title of his new game, Gen Atlas, means. And it seems like it carries more meaning than you might think. Read more",
      "date": "10 de junio de 2026",
      "source": "eurogamer.net",
      "tag": "Noticia"
    },
    {
      "id": "n12",
      "title": "Fire Emblem: Fortune's Weave's world map is partially inspired by medieval Spain, even if the Dagdan Empire setting looks much older",
      "titleEN": "Fire Emblem: Fortune's Weave's world map is partially inspired by medieval Spain, even if the Dagdan Empire setting looks much older",
      "desc": "Yesterday's Nintendo Direct was a meaty one, and one of its biggest announcements was the new look at Fire Emblem: Fortune's Weave (release date included); a new entry in the huge turn-based strategy-RPG series set in the Greece and Rome-inspired (bu",
      "descEN": "Yesterday's Nintendo Direct was a meaty one, and one of its biggest announcements was the new look at Fire Emblem: Fortune's Weave (release date included); a new entry in the huge turn-based strategy-RPG series set in the Greece and Rome-inspired (bu",
      "date": "10 de junio de 2026",
      "source": "eurogamer.net",
      "tag": "Hardware"
    }
  ]
}